secure_context/__init__.py
secure_context/_extensions/__init__.py
secure_context/_extensions/_edhc_curve.abi3.so
secure_context/_extensions/_edhc_curve.pyi
secure_context/ffdhe4096
secure_context/py.typed
secure_context/ssl_context.py
secure_context-2.0.0.dist-info/LICENSE
secure_context-2.0.0.dist-info/WHEEL
secure_context-2.0.0.dist-info/METADATA
secure_context-2.0.0.dist-info/RECORD
