Metadata-Version: 2.1
Name: secure-context
Version: 2.0.0
Summary: Utilities for creation of SSL/TLS security contexts for servers and clients
Home-page: https://gitlab.com/VitorVasconcellos/secure_context
License: BSD-3-Clause
Keywords: rsa,x509,openssl,security,certificate
Author: Vítor Vasconcellos
Author-email: vasconcellos.dev@gmail.com
Requires-Python: >=3.6,<4.0
Classifier: Development Status :: 5 - Production/Stable
Classifier: Intended Audience :: Developers
Classifier: License :: OSI Approved :: BSD License
Classifier: Operating System :: OS Independent
Classifier: Programming Language :: Python :: 3
Classifier: Programming Language :: Python :: 3.10
Classifier: Programming Language :: Python :: 3.6
Classifier: Programming Language :: Python :: 3.7
Classifier: Programming Language :: Python :: 3.8
Classifier: Programming Language :: Python :: 3.9
Classifier: Topic :: Internet :: WWW/HTTP :: HTTP Servers
Classifier: Topic :: Security
Classifier: Topic :: Software Development :: Libraries
Requires-Dist: importlib_metadata; python_version <= "3.8"
Requires-Dist: importlib_resources; python_version <= "3.9"
Project-URL: Bug Tracker, https://gitlab.com/VitorVasconcellos/secure_context/issues
Project-URL: Repository, https://gitlab.com/VitorVasconcellos/secure_context
